pbi/__init__.py
pbi/bookmark.py
pbi/config.py
pbi/container.py
pbi/filter.py
pbi/layout.py
pbi/object.py
pbi/page.py
pbi/pbi.py
pbi/report.py
pbi/utils.py
python_pbi-1.0.1.dist-info/LICENSE
python_pbi-1.0.1.dist-info/METADATA
python_pbi-1.0.1.dist-info/WHEEL
python_pbi-1.0.1.dist-info/top_level.txt
python_pbi-1.0.1.dist-info/RECORD
