Metadata-Version: 2.1
Name: python-pbi
Version: 1.0.1
Summary: Manipulate Power BI (.pbix) files
Author-email: Jeremy Chamboredon <jeremy.chamboredon@normalesup.org>
License: GNU GENERAL PUBLIC LICENSE
Project-URL: Home, https://github.com/JChamboredon/pbi
Classifier: License :: OSI Approved :: GNU General Public License v3 or later (GPLv3+)
License-File: LICENSE
Requires-Dist: pandas
